entity/__init__.py
entity/cli/__init__.py
entity/cli/__main__.py
entity/cli/commands/__init__.py
entity/cli/commands/init.py
entity/cli/commands/run.py
entity/cli/ent_cli_adapter.py
entity/cli/entity_main.py
entity/config/__init__.py
entity/config/validation.py
entity/config/variable_resolver.py
entity/core/__init__.py
entity/core/agent.py
entity/defaults.py
entity/infrastructure/__init__.py
entity/infrastructure/base.py
entity/infrastructure/config_models.py
entity/infrastructure/duckdb_infra.py
entity/infrastructure/local_storage_infra.py
entity/infrastructure/ollama_infra.py
entity/infrastructure/protocols.py
entity/infrastructure/s3_infra.py
entity/plugins/__init__.py
entity/plugins/base.py
entity/plugins/context.py
entity/plugins/defaults/__init__.py
entity/plugins/examples/__init__.py
entity/plugins/examples/calculator.py
entity/plugins/examples/input_reader.py
entity/plugins/examples/keyword_extractor.py
entity/plugins/examples/output_formatter.py
entity/plugins/examples/reason_generator.py
entity/plugins/examples/static_reviewer.py
entity/plugins/input_adapter.py
entity/plugins/output_adapter.py
entity/plugins/prompt.py
entity/plugins/smart_selector.py
entity/plugins/tool.py
entity/plugins/validation.py
entity/py.typed
entity/resources/__init__.py
entity/resources/argument_parsing.py
entity/resources/database.py
entity/resources/exceptions.py
entity/resources/file_storage_wrapper.py
entity/resources/llm.py
entity/resources/llm_protocol.py
entity/resources/llm_wrapper.py
entity/resources/local_storage.py
entity/resources/logging.py
entity/resources/memory.py
entity/resources/metrics.py
entity/resources/storage.py
entity/resources/vector_store.py
entity/setup/__init__.py
entity/setup/ollama_installer.py
entity/tools/__init__.py
entity/tools/registry.py
entity/tools/sandbox.py
entity/tools/web_search.py
entity/tools/workflow_viz.py
entity/workflow/__init__.py
entity/workflow/executor.py
entity/workflow/templates/__init__.py
entity/workflow/templates/basic.yaml
entity_core-0.0.12.dist-info/LICENSE
entity_core-0.0.12.dist-info/METADATA
entity_core-0.0.12.dist-info/WHEEL
entity_core-0.0.12.dist-info/entry_points.txt
entity_core-0.0.12.dist-info/RECORD
