Metadata-Version: 2.3
Name: entity-core
Version: 0.0.12
Summary: A flexible, plugin-based framework for building AI agents
License: MIT
Keywords: ai,agents,llm,framework,plugin,workflow,memory,rag,autonomous,assistant
Author: C. Thomas Brittain
Author-email: cthomasbrittain@hotmail.com
Requires-Python: >=3.11
Classifier: Development Status :: 3 - Alpha
Classifier: Intended Audience :: Developers
Classifier: Topic :: Software Development :: Libraries :: Python Modules
Classifier: Topic :: Scientific/Engineering :: Artificial Intelligence
Classifier: License :: OSI Approved :: MIT License
Classifier: Programming Language :: Python :: 3
Classifier: Programming Language :: Python :: 3.11
Classifier: Programming Language :: Python :: 3.12
Classifier: Operating System :: OS Independent
Classifier: Typing :: Typed
Classifier: Framework :: AsyncIO
Requires-Dist: aioboto3 (>=13.0.0,<14.0.0)
Requires-Dist: duckdb (>=1.3.1,<2.0.0)
Requires-Dist: grpcio (>=1.62.2,<2.0.0)
Requires-Dist: grpcio-tools (>=1.62.2,<2.0.0)
Requires-Dist: httpx (==0.27.*)
Requires-Dist: huggingface_hub (>=0.23,<0.24)
Requires-Dist: pydantic (>=2.0.0,<3.0.0)
Requires-Dist: pyyaml (>=6.0.2,<7.0.0)
Requires-Dist: rich (>=13.7,<14.0)
Requires-Dist: websockets (>=15.0,<16.0)
Project-URL: Bug Tracker, https://github.com/Ladvien/entity/issues
Project-URL: Discussions, https://github.com/Ladvien/entity/discussions
Project-URL: documentation, https://entity-core.readthedocs.io/en/latest/
Project-URL: homepage, https://github.com/Ladvien/entity
Project-URL: repository, https://github.com/Ladvien/entity
